HARK/SSJutils.py
HARK/__init__.py
HARK/core.py
HARK/dcegm.py
HARK/econforgeinterp.py
HARK/estimation.py
HARK/helpers.py
HARK/interpolation.py
HARK/mat_methods.py
HARK/metric.py
HARK/model.py
HARK/numba_tools.py
HARK/parser.py
HARK/rewards.py
HARK/simulator.py
HARK/utilities.py
HARK/validators.py
HARK/Calibration/__init__.py
HARK/Calibration/load_data.py
HARK/Calibration/Assets/AssetProcesses.py
HARK/Calibration/Assets/__init__.py
HARK/Calibration/Income/IncomeProcesses.py
HARK/Calibration/Income/IncomeTools.py
HARK/Calibration/Income/README.md
HARK/Calibration/Income/__init__.py
HARK/Calibration/SCF/__init__.py
HARK/Calibration/SCF/WealthIncomeDist/README.md
HARK/Calibration/SCF/WealthIncomeDist/SCFDistTools.py
HARK/Calibration/SCF/WealthIncomeDist/WealthIncomeStats.csv
HARK/Calibration/SCF/WealthIncomeDist/__init__.py
HARK/Calibration/cpi/__init__.py
HARK/Calibration/cpi/us/CPITools.py
HARK/Calibration/cpi/us/README.md
HARK/Calibration/cpi/us/__init__.py
HARK/Calibration/cpi/us/r-cpi-u-rs-allitems.csv
HARK/Calibration/data/EducMortAdj.txt
HARK/Calibration/data/SCFwealthDataReduced.txt
HARK/Calibration/data/USactuarial.txt
HARK/Calibration/data/__init__.py
HARK/Calibration/life_tables/__init__.py
HARK/Calibration/life_tables/us_ssa/PerLifeTables_F_Alt2_TR2020.csv
HARK/Calibration/life_tables/us_ssa/PerLifeTables_F_Hist_TR2020.csv
HARK/Calibration/life_tables/us_ssa/PerLifeTables_M_Alt2_TR2020.csv
HARK/Calibration/life_tables/us_ssa/PerLifeTables_M_Hist_TR2020.csv
HARK/Calibration/life_tables/us_ssa/README.md
HARK/Calibration/life_tables/us_ssa/SSATools.py
HARK/Calibration/life_tables/us_ssa/__init__.py
HARK/ConsumptionSaving/ConsAggShockModel.py
HARK/ConsumptionSaving/ConsBequestModel.py
HARK/ConsumptionSaving/ConsGenIncProcessModel.py
HARK/ConsumptionSaving/ConsHealthModel.py
HARK/ConsumptionSaving/ConsIndShockModel.py
HARK/ConsumptionSaving/ConsIndShockModelFast.py
HARK/ConsumptionSaving/ConsLabeledModel.py
HARK/ConsumptionSaving/ConsLaborModel.py
econ_ark-0.17.0.dist-info/licenses/LICENSE
econ_ark-0.17.0.dist-info/METADATA
econ_ark-0.17.0.dist-info/WHEEL
econ_ark-0.17.0.dist-info/top_level.txt
econ_ark-0.17.0.dist-info/RECORD
