Metadata-Version: 2.4
Name: econ-ark
Version: 0.17.0
Summary: Heterogenous Agents Resources & toolKit
Author-email: Econ-ARK team <econ-ark@jhuecon.org>
License-Expression: Apache-2.0
Project-URL: Homepage, https://github.com/econ-ark/HARK
Project-URL: Bug Reports, https://github.com/econ-ark/HARK/issues
Project-URL: Documentation, https://econ-ark.github.io/HARK
Keywords: economics,modelling,modeling,heterogeneity
Classifier: Development Status :: 3 - Alpha
Classifier: Environment :: Console
Classifier: Intended Audience :: Developers
Classifier: Intended Audience :: Financial and Insurance Industry
Classifier: Intended Audience :: Science/Research
Classifier: Topic :: Scientific/Engineering
Classifier: Topic :: Scientific/Engineering :: Mathematics
Classifier: Topic :: Other/Nonlisted Topic
Classifier: Natural Language :: English
Classifier: Operating System :: OS Independent
Classifier: Programming Language :: Python :: 3
Classifier: Programming Language :: Python :: 3.10
Classifier: Programming Language :: Python :: 3.11
Classifier: Programming Language :: Python :: 3.12
Classifier: Programming Language :: Python :: 3.13
Requires-Python: >=3.10
License-File: LICENSE
Requires-Dist: interpolation>=2.2.3
Requires-Dist: joblib>=1.2
Requires-Dist: legacy-cgi; python_version >= "3.13"
Requires-Dist: matplotlib>=3.6
Requires-Dist: networkx>=3
Requires-Dist: numba
Requires-Dist: numpy
Requires-Dist: optimagic
Requires-Dist: pandas>=1.5
Requires-Dist: pyyaml>=6.0
Requires-Dist: quantecon
Requires-Dist: scipy>=1.10
Requires-Dist: seaborn>=0.12
Requires-Dist: sequence-jacobian
Requires-Dist: statsmodels>=0.14.2
Requires-Dist: xarray>=2023
Provides-Extra: dev
Requires-Dist: nbval; extra == "dev"
Requires-Dist: pre-commit; extra == "dev"
Requires-Dist: pytest; extra == "dev"
Requires-Dist: pytest-cov; extra == "dev"
Requires-Dist: pytest-xdist; extra == "dev"
Requires-Dist: ruff; extra == "dev"
Provides-Extra: doc
Requires-Dist: ipython; extra == "doc"
Requires-Dist: myst-parser>=2; extra == "doc"
Requires-Dist: nbsphinx>=0.8; extra == "doc"
Requires-Dist: pydata-sphinx-theme; extra == "doc"
Requires-Dist: sphinx>=6.1; extra == "doc"
Requires-Dist: sphinx-copybutton; extra == "doc"
Requires-Dist: sphinx-design; extra == "doc"
Dynamic: license-file
